{
  "chrome": {
    "img-element": 0,
    "divbg-element": 1,
    "script-element": 4,
    "script-add": 1,
    "iframe-element": 1,
    "script-comment": 3,
    "img-add": 0,
    "divbg-add": 4,
    "style-add": 1,
    "webfont-range": 3,
    "resize-reload": 1
  },
  "opera": {
    "img-element": 0,
    "divbg-element": 2,
    "script-element": 0,
    "script-add": 2,
    "iframe-element": 2,
    "script-comment": 3,
    "img-add": 0,
    "divbg-add": 5,
    "style-add": 2,
    "webfont-range": 2,
    "resize-reload": 1
  },
  "firefox": {
    "img-element": 0,
    "divbg-element": 2,
    "script-element": 0,
    "script-add": 1,
    "iframe-element": 2,
    "script-comment": 0,
    "img-add": 0,
    "divbg-add": 4,
    "style-add": 1,
    "webfont-range": 2,
    "resize-reload": 2
  },
  "ie": {}
}